xr_tui/cli.py
xr_tui/hdf_reader.py
xr_tui/plotting.py
xr_tui/xr-tui.tcss
xr_tui-2025.2.0.dist-info/licenses/LICENSE
xr_tui-2025.2.0.dist-info/METADATA
xr_tui-2025.2.0.dist-info/WHEEL
xr_tui-2025.2.0.dist-info/entry_points.txt
xr_tui-2025.2.0.dist-info/top_level.txt
xr_tui-2025.2.0.dist-info/RECORD
