Metadata-Version: 2.4
Name: xr-tui
Version: 2025.2.0
Summary: A Textual User Interface (TUI) for exploring xarray Datasets.
Author-email: Samuel Jackson <samuel.jackson@outlook.com>
Maintainer-email: Samuel Jackson <samuel.jackson@outlook.com>
License: MIT
Classifier: Development Status :: 4 - Beta
Classifier: Programming Language :: Python
Requires-Python: >=3.11
License-File: LICENSE
Requires-Dist: fsspec[s3]>=2025.10.0
Requires-Dist: scipy>=1.13.1
Requires-Dist: textual>=6.7.1
Requires-Dist: textual-plotext>=1.0.1
Requires-Dist: textual-slider>=0.2.0
Requires-Dist: xarray[io]>=2024.7.0
Requires-Dist: zarr>=2.18.2
Dynamic: license-file
